{"name": "MUZRTO", "gen": 237, "mutations": 5, "size": 10.0, "power": 8, "food": 8, "speed": 10, "eyes": 1, "color0": [255, 0, 0, 255], "color1": [135, 206, 235, 255], "color2": [0, 0, 255, 80], "color3": [255, 0, 0, 255], "neuro": {"layer_num": 9, "node_num": 15, "link_num": 29, "layers": {"0": {"type": 0, "nodes": "[9447, 9904, 9818, 4930, 5126, 7300, 3895, 3599, 7520, 1911, 8519, 2659, 8959, 3189, 4372, 9761]"}, "1": {"type": 1, "nodes": "[9546, 4576]"}, "2": {"type": 1, "nodes": "[]"}, "3": {"type": 1, "nodes": "[7332, 9901, 7888, 8693, 8904]"}, "4": {"type": 1, "nodes": "[9721]"}, "5": {"type": 1, "nodes": "[7791, 6497, 4110]"}, "6": {"type": 1, "nodes": "[]"}, "7": {"type": 1, "nodes": "[3204, 1364, 1223, 9965]"}, "8": {"type": 2, "nodes": "[1932, 3266, 7877, 1538, 7113]"}}, "nodes": {"9447": {"type": 0, "recurrent": "1", "mem_weight": 0.23663699503174923, "bias": -0.18817572792829315, "from_links": "[1530]", "to_links": "[]", "activation": 0}, "9904": {"type": 0, "recurrent": "1", "mem_weight": -0.29550935526070976, "bias": -0.3231683539315712, "from_links": "[]", "to_links": "[]", "activation": 0}, "9818": {"type": 0, "recurrent": "1", "mem_weight": 0.06410168953410653, "bias": -0.03493653333790904, "from_links": "[5977, 6928, 1541]", "to_links": "[]", "activation": 0}, "4930": {"type": 0, "recurrent": "1", "mem_weight": -0.3787818391641199, "bias": -0.225509008646461, "from_links": "[]", "to_links": "[]", "activation": 0}, "5126": {"type": 0, "recurrent": "0", "mem_weight": null, "bias": 0.29209016949081534, "from_links": "[5330, 1193]", "to_links": "[]", "activation": 0}, "7300": {"type": 0, "recurrent": "0", "mem_weight": null, "bias": -0.3183159036433387, "from_links": "[6485]", "to_links": "[]", "activation": 0}, "3895": {"type": 0, "recurrent": "1", "mem_weight": 0.0001962918746811724, "bias": 0.5718422647600787, "from_links": "[9877, 4104]", "to_links": "[]", "activation": 0}, "3599": {"type": 0, "recurrent": "0", "mem_weight": null, "bias": -0.3360323958482194, "from_links": "[3287]", "to_links": "[]", "activation": 0}, "7520": {"type": 0, "recurrent": "1", "mem_weight": -0.07610276690757212, "bias": 0.47402147993484334, "from_links": "[]", "to_links": "[]", "activation": 0}, "1911": {"type": 0, "recurrent": "0", "mem_weight": null, "bias": -0.0010940636909662345, "from_links": "[]", "to_links": "[]", "activation": 0}, "8519": {"type": 0, "recurrent": "1", "mem_weight": -0.23107077701460893, "bias": -0.45188197751031967, "from_links": "[3057, 1848]", "to_links": "[]", "activation": 0}, "2659": {"type": 0, "recurrent": "1", "mem_weight": 0.12511247573733422, "bias": -1, "from_links": "[]", "to_links": "[]", "activation": 0}, "8959": {"type": 0, "recurrent": "0", "mem_weight": null, "bias": 0.5311107674706738, "from_links": "[2320, 1041]", "to_links": "[]", "activation": 0}, "3189": {"type": 0, "recurrent": "1", "mem_weight": 0.0053074341661666505, "bias": -0.19535928042560455, "from_links": "[6937]", "to_links": "[]", "activation": 0}, "4372": {"type": 0, "recurrent": "0", "mem_weight": null, "bias": 0.26897038972053394, "from_links": "[4188]", "to_links": "[]", "activation": 0}, "9761": {"type": 0, "recurrent": "1", "mem_weight": 0.32144352643772134, "bias": 0.6340343236613587, "from_links": "[]", "to_links": "[]", "activation": 0}, "1932": {"type": 2, "recurrent": "1", "mem_weight": 1, "bias": 0.6390285184849868, "from_links": "[]", "to_links": "[3874]", "activation": 0}, "3266": {"type": 2, "recurrent": "0", "mem_weight": null, "bias": 0.3826136129250518, "from_links": "[]", "to_links": "[6485, 4222, 9434, 6374, 6436, 1371, 7727]", "activation": 0}, "7877": {"type": 2, "recurrent": "1", "mem_weight": -0.29092173633410523, "bias": 0.6060312846143721, "from_links": "[]", "to_links": "[]", "activation": 0}, "1538": {"type": 2, "recurrent": "1", "mem_weight": 0.373842339477494, "bias": 1, "from_links": "[]", "to_links": "[1193, 6872, 6928, 7495, 2622]", "activation": 0}, "7113": {"type": 2, "recurrent": "0", "mem_weight": null, "bias": 0.15605419234507806, "from_links": "[]", "to_links": "[3057, 1061, 4528, 2581]", "activation": 0}, "7791": {"type": 1, "recurrent": "1", "mem_weight": 0.007622218395517314, "bias": 0.3840842579485193, "from_links": "[]", "to_links": "[4188, 9877]", "activation": 0}, "9546": {"type": 1, "recurrent": "0", "mem_weight": null, "bias": 1, "from_links": "[3874]", "to_links": "[]", "activation": 0}, "6497": {"type": 1, "recurrent": "1", "mem_weight": 0.01296984555090053, "bias": -0.5811158925994243, "from_links": "[]", "to_links": "[5977]", "activation": 0}, "9721": {"type": 1, "recurrent": "0", "mem_weight": null, "bias": 1, "from_links": "[7495]", "to_links": "[]", "activation": 0}, "7332": {"type": 1, "recurrent": "0", "mem_weight": null, "bias": -0.10526111953683089, "from_links": "[]", "to_links": "[5330]", "activation": 0}, "3204": {"type": 1, "recurrent": "0", "mem_weight": null, "bias": 0.12380775964536775, "from_links": "[4222]", "to_links": "[]", "activation": 0}, "1364": {"type": 1, "recurrent": "0", "mem_weight": null, "bias": 0.8689760495153644, "from_links": "[9434]", "to_links": "[]", "activation": 0}, "1223": {"type": 1, "recurrent": "0", "mem_weight": null, "bias": 0.5962307180237519, "from_links": "[6374, 1061]", "to_links": "[]", "activation": 0}, "9901": {"type": 1, "recurrent": "1", "mem_weight": -1, "bias": -0.20352003089342272, "from_links": "[6436]", "to_links": "[2320]", "activation": 0}, "9965": {"type": 1, "recurrent": "1", "mem_weight": 0.1798802248767055, "bias": 0.215186157897186, "from_links": "[6872]", "to_links": "[4104]", "activation": 0}, "7888": {"type": 1, "recurrent": "1", "mem_weight": -0.02612756246688239, "bias": 0.18517387701694862, "from_links": "[1371]", "to_links": "[6937, 3287]", "activation": 0}, "4576": {"type": 1, "recurrent": "1", "mem_weight": 0.0004165445048141859, "bias": -0.28627896204345626, "from_links": "[2622]", "to_links": "[1530]", "activation": 0}, "8693": {"type": 1, "recurrent": "1", "mem_weight": 0.23351875601648925, "bias": -0.5194361865308676, "from_links": "[7727]", "to_links": "[1848]", "activation": 0}, "8904": {"type": 1, "recurrent": "0", "mem_weight": null, "bias": -0.11403467780714223, "from_links": "[4528]", "to_links": "[1041]", "activation": 0}, "4110": {"type": 1, "recurrent": "0", "mem_weight": null, "bias": -0.5469028627907059, "from_links": "[2581]", "to_links": "[1541]", "activation": 0}}, "links": {"6485": {"weight": 0.667781841344397, "from_node": 7300, "to_node": 3266}, "3057": {"weight": -0.556010449123758, "from_node": 8519, "to_node": 7113}, "3874": {"weight": 0.06606824445042035, "from_node": 9546, "to_node": 1932}, "4188": {"weight": 0.6378536321863373, "from_node": 4372, "to_node": 7791}, "5330": {"weight": -0.1437314401968049, "from_node": 5126, "to_node": 7332}, "4222": {"weight": 0.2353067563188161, "from_node": 3204, "to_node": 3266}, "9434": {"weight": -0.15436205372255127, "from_node": 1364, "to_node": 3266}, "9877": {"weight": 0.42627209694120777, "from_node": 3895, "to_node": 7791}, "5977": {"weight": 0.1469347464613864, "from_node": 9818, "to_node": 6497}, "1193": {"weight": -0.6486931588003267, "from_node": 5126, "to_node": 1538}, "6374": {"weight": -0.7434046458736894, "from_node": 1223, "to_node": 3266}, "2320": {"weight": 0.9559246783337574, "from_node": 8959, "to_node": 9901}, "6436": {"weight": 0.12765332468544982, "from_node": 9901, "to_node": 3266}, "4104": {"weight": -0.3588733510544184, "from_node": 3895, "to_node": 9965}, "6872": {"weight": -0.3546275290731859, "from_node": 9965, "to_node": 1538}, "6928": {"weight": -0.5380342562973048, "from_node": 9818, "to_node": 1538}, "6937": {"weight": 0.6440202740784231, "from_node": 3189, "to_node": 7888}, "1371": {"weight": -0.28437263520605194, "from_node": 7888, "to_node": 3266}, "7495": {"weight": 0.8829197506986843, "from_node": 9721, "to_node": 1538}, "1061": {"weight": 0.029923118989017134, "from_node": 1223, "to_node": 7113}, "1530": {"weight": -0.23757563032619258, "from_node": 9447, "to_node": 4576}, "2622": {"weight": -0.2607496339156563, "from_node": 4576, "to_node": 1538}, "1848": {"weight": 1, "from_node": 8519, "to_node": 8693}, "7727": {"weight": 0.4104502481929251, "from_node": 8693, "to_node": 3266}, "1041": {"weight": 0.7651222351934768, "from_node": 8959, "to_node": 8904}, "4528": {"weight": 0.18669663338052145, "from_node": 8904, "to_node": 7113}, "1541": {"weight": -0.1643941013456643, "from_node": 9818, "to_node": 4110}, "2581": {"weight": 0.022984342218521966, "from_node": 4110, "to_node": 7113}, "3287": {"weight": 0.9880434450596829, "from_node": 3599, "to_node": 7888}}}, "signature": [[10, 6, 9, 2], [6485, 3057, 3874, 4188, 4286, 5330, 4222, 9434, 9877, 5977, 1193, 6374, 2320, 6436, 4104, 6872, 6928, 6937, 1371, 7495, 1101, 1061, 1530, 2622]], "genealogy": [["CEFIQE", 51, 139720], ["CEFINU", 51, 139967], ["CENIJI", 51, 140069], ["CEUIJI", 51, 140121], ["CEFIVJ", 51, 140165], ["CEFIPI", 79, 146871], ["CEFIZY", 97, 149707], ["MSFIZY", 117, 155757], ["MSIWZY", 121, 157087], ["MSIWTO", 131, 158520], ["MSFFTO", 149, 148917], ["VFIWTO", 153, 151226], ["VFZRTO", 178, 156264], ["VFXFTO", 213, 160653], ["MUZRTO", 213, 161017]]}