{"name": "NLDJZE", "gen": 44, "mutations": 7, "size": 10.0, "power": 2, "food": 10, "speed": 10, "eyes": 4, "color0": [0, 0, 0, 255], "color1": [135, 206, 235, 255], "color2": [0, 0, 255, 255], "color3": [255, 0, 0, 255], "neuro": {"layer_num": 9, "node_num": 22, "link_num": 52, "layers": {"0": {"type": 0, "nodes": "[6988, 4789, 3249, 5091, 8016, 7342, 1021, 7421, 8397, 4126, 1650, 3504, 2925, 7840, 3847, 2942]"}, "1": {"type": 1, "nodes": "[5393, 6202, 8901]"}, "2": {"type": 1, "nodes": "[]"}, "3": {"type": 1, "nodes": "[6061, 3238, 1292, 2110]"}, "4": {"type": 1, "nodes": "[7703, 7254, 4678, 9405]"}, "5": {"type": 1, "nodes": "[1066, 8566, 3762, 7673]"}, "6": {"type": 1, "nodes": "[1307, 9129, 1724]"}, "7": {"type": 1, "nodes": "[1563, 9300, 3734, 7539]"}, "8": {"type": 2, "nodes": "[1974, 3872, 5530, 7150, 9145]"}}, "nodes": {"6988": {"type": 0, "recurrent": "0", "mem_weight": null, "bias": -1, "from_links": "[1784, 1534]", "to_links": "[]", "activation": 0}, "4789": {"type": 0, "recurrent": "0", "mem_weight": null, "bias": -0.23360613240755804, "from_links": "[6121, 8735]", "to_links": "[]", "activation": 0}, "3249": {"type": 0, "recurrent": "0", "mem_weight": null, "bias": 0.25360268603745345, "from_links": "[1496]", "to_links": "[]", "activation": 0}, "5091": {"type": 0, "recurrent": "0", "mem_weight": null, "bias": -0.5077340407642519, "from_links": "[7300]", "to_links": "[]", "activation": 0}, "8016": {"type": 0, "recurrent": "0", "mem_weight": null, "bias": -0.37821654432687773, "from_links": "[1171, 9375, 8285, 4212]", "to_links": "[]", "activation": 0}, "7342": {"type": 0, "recurrent": "0", "mem_weight": null, "bias": 0.2113463616971211, "from_links": "[1259, 1118, 1721]", "to_links": "[]", "activation": 0}, "1021": {"type": 0, "recurrent": "1", "mem_weight": -1, "bias": 0.5136844256076281, "from_links": "[7458, 8872, 6764]", "to_links": "[]", "activation": 0}, "7421": {"type": 0, "recurrent": "1", "mem_weight": 0.037030455774453054, "bias": 0.4885275411637814, "from_links": "[]", "to_links": "[]", "activation": 0}, "8397": {"type": 0, "recurrent": "0", "mem_weight": null, "bias": -0.3193712761576635, "from_links": "[5047, 9002, 6757]", "to_links": "[]", "activation": 0}, "4126": {"type": 0, "recurrent": "1", "mem_weight": 0.11398389541236881, "bias": -0.31049514719680155, "from_links": "[]", "to_links": "[]", "activation": 0}, "1650": {"type": 0, "recurrent": "0", "mem_weight": null, "bias": -0.30639567404549717, "from_links": "[1873]", "to_links": "[]", "activation": 0}, "3504": {"type": 0, "recurrent": "1", "mem_weight": 0.03781346615945603, "bias": 0.14270081534035997, "from_links": "[7173, 3350, 3078]", "to_links": "[]", "activation": 0}, "2925": {"type": 0, "recurrent": "0", "mem_weight": null, "bias": -0.9346834390954208, "from_links": "[5870, 3478, 7598]", "to_links": "[]", "activation": 0}, "7840": {"type": 0, "recurrent": "0", "mem_weight": null, "bias": -0.5719325697595472, "from_links": "[8965, 1789]", "to_links": "[]", "activation": 0}, "3847": {"type": 0, "recurrent": "1", "mem_weight": 0.052592153509185155, "bias": 0.9802049379899411, "from_links": "[2953, 9939, 3923]", "to_links": "[]", "activation": 0}, "2942": {"type": 0, "recurrent": "1", "mem_weight": -0.10000103265417051, "bias": -0.556938659129799, "from_links": "[1700, 7555]", "to_links": "[]", "activation": 0}, "1974": {"type": 2, "recurrent": "0", "mem_weight": null, "bias": 0.6330125195378087, "from_links": "[]", "to_links": "[2953, 7286, 1314]", "activation": 0}, "3872": {"type": 2, "recurrent": "0", "mem_weight": null, "bias": -0.14974915379547063, "from_links": "[]", "to_links": "[1259, 3170, 3929, 3162, 5301, 4273]", "activation": 0}, "5530": {"type": 2, "recurrent": "1", "mem_weight": -0.0033852911259424382, "bias": -0.44207280283811196, "from_links": "[]", "to_links": "[7564, 7308, 8160, 1493]", "activation": 0}, "7150": {"type": 2, "recurrent": "1", "mem_weight": 0.24150010834932148, "bias": 0.15418636692801221, "from_links": "[]", "to_links": "[9939, 6757, 1789, 8285]", "activation": 0}, "9145": {"type": 2, "recurrent": "0", "mem_weight": null, "bias": -0.19187768495849192, "from_links": "[]", "to_links": "[7458, 5047, 1118, 9480, 4075, 8831, 3440, 8339]", "activation": 0}, "1307": {"type": 1, "recurrent": "0", "mem_weight": null, "bias": -0.48208209012628717, "from_links": "[]", "to_links": "[9002, 1354]", "activation": 0}, "9129": {"type": 1, "recurrent": "0", "mem_weight": null, "bias": 1, "from_links": "[]", "to_links": "[5870]", "activation": 0}, "1066": {"type": 1, "recurrent": "0", "mem_weight": null, "bias": 0.16036656247031217, "from_links": "[]", "to_links": "[3478]", "activation": 0}, "5393": {"type": 1, "recurrent": "1", "mem_weight": 0.0010079970696607304, "bias": -0.384111508260791, "from_links": "[7564, 9534]", "to_links": "[]", "activation": 0}, "1563": {"type": 1, "recurrent": "0", "mem_weight": null, "bias": -0.01800819253782904, "from_links": "[9480]", "to_links": "[1784, 6121]", "activation": 0}, "1724": {"type": 1, "recurrent": "0", "mem_weight": null, "bias": 0.20029407546318864, "from_links": "[]", "to_links": "[1534, 2360]", "activation": 0}, "8566": {"type": 1, "recurrent": "0", "mem_weight": null, "bias": 0.281805920865655, "from_links": "[]", "to_links": "[1171]", "activation": 0}, "7703": {"type": 1, "recurrent": "0", "mem_weight": null, "bias": -0.594197247488042, "from_links": "[1354]", "to_links": "[1700]", "activation": 0}, "6061": {"type": 1, "recurrent": "0", "mem_weight": null, "bias": -0.886446323895463, "from_links": "[7308, 2360]", "to_links": "[1721]", "activation": 0}, "3238": {"type": 1, "recurrent": "1", "mem_weight": -1, "bias": -0.6208889065682617, "from_links": "[4075]", "to_links": "[9375, 7173]", "activation": 0}, "6202": {"type": 1, "recurrent": "0", "mem_weight": null, "bias": -0.40166043005879615, "from_links": "[7286]", "to_links": "[1496]", "activation": 0}, "8901": {"type": 1, "recurrent": "1", "mem_weight": -0.4749262559391594, "bias": -0.8667015981304708, "from_links": "[8831]", "to_links": "[]", "activation": 0}, "7254": {"type": 1, "recurrent": "0", "mem_weight": null, "bias": -0.12729597515467306, "from_links": "[8160]", "to_links": "[8872]", "activation": 0}, "9300": {"type": 1, "recurrent": "0", "mem_weight": null, "bias": 0.1823275930031328, "from_links": "[1493]", "to_links": "[8965, 9534]", "activation": 0}, "3762": {"type": 1, "recurrent": "0", "mem_weight": null, "bias": -0.45707745847851383, "from_links": "[3170]", "to_links": "[3923]", "activation": 0}, "7673": {"type": 1, "recurrent": "0", "mem_weight": null, "bias": 0.1643485624147117, "from_links": "[3929]", "to_links": "[7300, 7555, 7598]", "activation": 0}, "3734": {"type": 1, "recurrent": "0", "mem_weight": null, "bias": 0.6440132197408255, "from_links": "[3440]", "to_links": "[6764]", "activation": 0}, "4678": {"type": 1, "recurrent": "0", "mem_weight": null, "bias": -1, "from_links": "[8339]", "to_links": "[8735]", "activation": 0}, "7539": {"type": 1, "recurrent": "1", "mem_weight": -0.4327264116464523, "bias": -0.3431893720473256, "from_links": "[3162]", "to_links": "[3350]", "activation": 0}, "1292": {"type": 1, "recurrent": "1", "mem_weight": -0.22973849627154636, "bias": -0.6653927611599885, "from_links": "[5301]", "to_links": "[3078]", "activation": 0}, "9405": {"type": 1, "recurrent": "0", "mem_weight": null, "bias": -0.8366826273562868, "from_links": "[4273]", "to_links": "[4212]", "activation": 0}, "2110": {"type": 1, "recurrent": "0", "mem_weight": null, "bias": 0.28364959056549555, "from_links": "[1314]", "to_links": "[1873]", "activation": 0}}, "links": {"2953": {"weight": 0.12097508631489003, "from_node": 3847, "to_node": 1974}, "1259": {"weight": 1, "from_node": 7342, "to_node": 3872}, "9939": {"weight": -0.8060474086149693, "from_node": 3847, "to_node": 7150}, "7458": {"weight": -0.42060537758738226, "from_node": 1021, "to_node": 9145}, "5047": {"weight": -0.11247261629707365, "from_node": 8397, "to_node": 9145}, "1118": {"weight": -0.4696528994264717, "from_node": 7342, "to_node": 9145}, "5870": {"weight": -0.21398593374002764, "from_node": 2925, "to_node": 9129}, "9002": {"weight": 0.17688600179619543, "from_node": 8397, "to_node": 1307}, "3478": {"weight": -0.30778832602421663, "from_node": 2925, "to_node": 1066}, "7564": {"weight": -0.5159953846545496, "from_node": 5393, "to_node": 5530}, "9480": {"weight": 0.20123640386741756, "from_node": 1563, "to_node": 9145}, "1784": {"weight": 0.17302232984788304, "from_node": 6988, "to_node": 1563}, "1534": {"weight": 0.5838704831845452, "from_node": 6988, "to_node": 1724}, "6121": {"weight": 0.043007338443819744, "from_node": 4789, "to_node": 1563}, "1171": {"weight": -0.2668639076204906, "from_node": 8016, "to_node": 8566}, "1354": {"weight": 0.6105939065858245, "from_node": 7703, "to_node": 1307}, "7308": {"weight": -0.43715752979918404, "from_node": 6061, "to_node": 5530}, "9375": {"weight": 0.6619821292840976, "from_node": 8016, "to_node": 3238}, "4075": {"weight": 0.0741070739265189, "from_node": 3238, "to_node": 9145}, "1496": {"weight": -0.2924217760126976, "from_node": 3249, "to_node": 6202}, "7286": {"weight": -0.6820264799167078, "from_node": 6202, "to_node": 1974}, "8831": {"weight": 0.1606121803268964, "from_node": 8901, "to_node": 9145}, "7173": {"weight": -1, "from_node": 3504, "to_node": 3238}, "8872": {"weight": 1, "from_node": 1021, "to_node": 7254}, "8160": {"weight": -0.5740771022222039, "from_node": 7254, "to_node": 5530}, "8965": {"weight": -0.2500468731180808, "from_node": 7840, "to_node": 9300}, "1493": {"weight": -0.1903771955812602, "from_node": 9300, "to_node": 5530}, "3923": {"weight": -0.384920537267725, "from_node": 3847, "to_node": 3762}, "3170": {"weight": 0.05963730327976213, "from_node": 3762, "to_node": 3872}, "7300": {"weight": -0.3310075472445506, "from_node": 5091, "to_node": 7673}, "3929": {"weight": -0.38977505796201545, "from_node": 7673, "to_node": 3872}, "6764": {"weight": 0.7701465142888025, "from_node": 1021, "to_node": 3734}, "3440": {"weight": -0.4604910008025555, "from_node": 3734, "to_node": 9145}, "1700": {"weight": -0.2870118270850584, "from_node": 2942, "to_node": 7703}, "8735": {"weight": 0.17542488261366423, "from_node": 4789, "to_node": 4678}, "8339": {"weight": 0.346647039589087, "from_node": 4678, "to_node": 9145}, "6757": {"weight": -0.7656848524250529, "from_node": 8397, "to_node": 7150}, "2360": {"weight": 0.2634173418346452, "from_node": 6061, "to_node": 1724}, "3350": {"weight": 0.566274288895491, "from_node": 3504, "to_node": 7539}, "3162": {"weight": 0.9756962000545901, "from_node": 7539, "to_node": 3872}, "1789": {"weight": -0.3441837819760743, "from_node": 7840, "to_node": 7150}, "3078": {"weight": 0.18766855679207858, "from_node": 3504, "to_node": 1292}, "5301": {"weight": -0.08470319325397975, "from_node": 1292, "to_node": 3872}, "7555": {"weight": -0.24191612433061815, "from_node": 2942, "to_node": 7673}, "7598": {"weight": -0.46315284808414053, "from_node": 2925, "to_node": 7673}, "8285": {"weight": -0.01736880633397234, "from_node": 8016, "to_node": 7150}, "4212": {"weight": 0.014140166070238401, "from_node": 8016, "to_node": 9405}, "4273": {"weight": 0.45440727032292616, "from_node": 9405, "to_node": 3872}, "9534": {"weight": -1, "from_node": 5393, "to_node": 9300}, "1873": {"weight": -0.5501848664154853, "from_node": 1650, "to_node": 2110}, "1314": {"weight": -0.23534927780540105, "from_node": 2110, "to_node": 1974}, "1721": {"weight": -0.3340622053888067, "from_node": 7342, "to_node": 6061}}}, "signature": [[10, 2, 10, 3], [2953, 1259, 9939, 7458, 5047, 1118, 5870, 9002, 3478, 7564, 9480, 1784, 1534, 6121, 1171, 1354, 7308, 9375, 4075, 1496, 7286, 8831, 7173, 8872, 8160, 8965, 1493, 3923, 3170, 7300, 3929, 6764, 3440, 1700, 8735, 8339, 6757, 2360, 3350, 3162, 1789, 3078, 5301, 7555, 7598, 8285, 4212, 4273, 9534, 1873, 1314]], "genealogy": [["QIDJPT", 0, 29287], ["QIDJFV", 8, 30485], ["QINEFV", 13, 31418], ["QIDJVY", 15, 31817], ["QIDJLI", 15, 31832], ["QIHSLI", 22, 32691], ["QIDJRP", 22, 32905], ["QIDJMI", 22, 33201], ["QIDJIY", 22, 33272], ["QIDJRJ", 22, 33392], ["QISSLI", 22, 33394], ["QIDJZE", 22, 33581], ["QIDJOK", 34, 35945], ["QIRLZE", 34, 36013], ["NFDJZE", 34, 36014], ["NFSVZE", 43, 37911], ["NFHFZE", 43, 37998], ["NFDJNT", 43, 38144], ["NFDJNF", 43, 38256], ["NODJZE", 43, 38327], ["NFFDZE", 43, 38448], ["NLDJZE", 43, 38552]]}