{"name": "BZBODY", "gen": 10, "mutations": 4, "size": 8.0, "power": 1, "food": 5, "speed": 7, "color0": [0, 0, 0, 255], "color1": [135, 206, 235, 255], "color2": [0, 0, 255, 255], "color3": [255, 0, 0, 255], "neuro": {"layer_num": 9, "node_num": 0, "link_num": 0, "layers": {"0": {"type": 0, "nodes": "[1723, 3805, 5854, 9588, 4996, 8016, 8697, 6756, 8513, 5609, 3546, 5287, 1445, 4178, 3821, 9148, 1767]"}, "1": {"type": 1, "nodes": "[1869, 8228, 5363, 7438]"}, "2": {"type": 1, "nodes": "[]"}, "3": {"type": 1, "nodes": "[3424, 7368, 9986]"}, "4": {"type": 1, "nodes": "[1470, 1824, 7776, 2213, 1294]"}, "5": {"type": 1, "nodes": "[9981, 4537, 4834, 1194, 4844, 3633, 3874]"}, "6": {"type": 1, "nodes": "[3138, 3105, 7319, 1154, 5555, 5910, 4479, 5089, 6863, 6291]"}, "7": {"type": 1, "nodes": "[2051, 1143, 4135, 6868, 2584, 1770]"}, "8": {"type": 2, "nodes": "[5002, 6785, 3615, 1103, 3505, 8744, 5010]"}}, "nodes": {"1723": {"type": 0, "recurrent": "0", "mem_weight": null, "bias": -0.8100307575617093, "from_links": "[8178, 1138, 3685, 7660]", "to_links": "[]", "activation": 1}, "3805": {"type": 0, "recurrent": "0", "mem_weight": null, "bias": 0.03868567356017883, "from_links": "[]", "to_links": "[]", "activation": 0}, "5854": {"type": 0, "recurrent": "1", "mem_weight": -1, "bias": -0.17903893156404646, "from_links": "[]", "to_links": "[]", "activation": 1}, "9588": {"type": 0, "recurrent": "0", "mem_weight": null, "bias": -0.2477910961102636, "from_links": "[5656, 6002, 3637, 2292]", "to_links": "[]", "activation": 3}, "4996": {"type": 0, "recurrent": "0", "mem_weight": null, "bias": -0.7882299916105672, "from_links": "[6765, 2311, 2768, 1237, 9076, 2359]", "to_links": "[]", "activation": 1}, "8016": {"type": 0, "recurrent": "0", "mem_weight": null, "bias": 0.46990735671454154, "from_links": "[]", "to_links": "[]", "activation": 2}, "8697": {"type": 0, "recurrent": "1", "mem_weight": 0.1537054666882413, "bias": -0.040326296045249725, "from_links": "[7677, 3565, 3070]", "to_links": "[]", "activation": 1}, "6756": {"type": 0, "recurrent": "0", "mem_weight": null, "bias": -0.9429281316327027, "from_links": "[2280, 6529, 7068, 8124, 5301]", "to_links": "[]", "activation": 1}, "8513": {"type": 0, "recurrent": "1", "mem_weight": 0.6096985700679481, "bias": 0.2510866499016896, "from_links": "[3071, 1383, 8697]", "to_links": "[]", "activation": 3}, "5609": {"type": 0, "recurrent": "0", "mem_weight": null, "bias": 0.10351840183300905, "from_links": "[6471, 2658, 7787, 6038]", "to_links": "[]", "activation": 2}, "3546": {"type": 0, "recurrent": "0", "mem_weight": null, "bias": 0.10062061051553556, "from_links": "[4026, 9671, 5264, 7379, 1150, 5542]", "to_links": "[]", "activation": 0}, "5287": {"type": 0, "recurrent": "0", "mem_weight": null, "bias": -0.05650907450494022, "from_links": "[4085, 4407]", "to_links": "[]", "activation": 1}, "1445": {"type": 0, "recurrent": "0", "mem_weight": null, "bias": -0.1781425257120958, "from_links": "[1368, 3172, 7323]", "to_links": "[]", "activation": 2}, "4178": {"type": 0, "recurrent": "0", "mem_weight": null, "bias": -0.05073993785031203, "from_links": "[2316, 2665]", "to_links": "[]", "activation": 1}, "3821": {"type": 0, "recurrent": "1", "mem_weight": -0.6437527435231716, "bias": 0.2534350491979814, "from_links": "[2985, 3250]", "to_links": "[]", "activation": 1}, "9148": {"type": 0, "recurrent": "1", "mem_weight": 0.5913785734880374, "bias": 0.3846733836537082, "from_links": "[]", "to_links": "[]", "activation": 0}, "1767": {"type": 0, "recurrent": "1", "mem_weight": 0.0019209631579669845, "bias": -0.6201119000151389, "from_links": "[1440, 9654]", "to_links": "[]", "activation": 0}, "5002": {"type": 2, "recurrent": "0", "mem_weight": null, "bias": 0.4161834186693214, "from_links": "[]", "to_links": "[2316, 8378, 1743, 4304, 1540, 6993, 4065, 6699]", "activation": 3}, "6785": {"type": 2, "recurrent": "1", "mem_weight": -0.34556235176200334, "bias": 0.0014493251683736959, "from_links": "[]", "to_links": "[6136, 7747, 6230, 1122, 1104]", "activation": 0}, "3615": {"type": 2, "recurrent": "0", "mem_weight": null, "bias": 0.3068481768207983, "from_links": "[]", "to_links": "[3071, 3300, 6657, 9480]", "activation": 0}, "1103": {"type": 2, "recurrent": "1", "mem_weight": -0.26427903045573653, "bias": 0.6816648480645149, "from_links": "[]", "to_links": "[2985, 4872, 6765, 4237, 7954]", "activation": 0}, "3505": {"type": 2, "recurrent": "1", "mem_weight": -0.37262259807082593, "bias": -0.16344376935181754, "from_links": "[]", "to_links": "[5912]", "activation": 1}, "8744": {"type": 2, "recurrent": "1", "mem_weight": -0.41285070172318455, "bias": -0.045530732020336154, "from_links": "[]", "to_links": "[5026, 1577, 3173, 8878, 7346, 3337, 3877]", "activation": 2}, "5010": {"type": 2, "recurrent": "0", "mem_weight": null, "bias": -0.5710443448944056, "from_links": "[]", "to_links": "[5656, 4079, 2594, 6544, 3385]", "activation": 0}, "1869": {"type": 1, "recurrent": "1", "mem_weight": 0.40403024392613873, "bias": -0.7371120535397905, "from_links": "[]", "to_links": "[1150]", "activation": 0}, "2051": {"type": 1, "recurrent": "0", "mem_weight": null, "bias": -0.574714647401364, "from_links": "[]", "to_links": "[6002]", "activation": 1}, "9981": {"type": 1, "recurrent": "1", "mem_weight": 0.5565793578926951, "bias": 0.5139257130446957, "from_links": "[]", "to_links": "[3565]", "activation": 1}, "3138": {"type": 1, "recurrent": "0", "mem_weight": null, "bias": -0.24873481375459805, "from_links": "[8378]", "to_links": "[3250, 7787]", "activation": 1}, "4537": {"type": 1, "recurrent": "1", "mem_weight": -0.3721145187524984, "bias": 0.09929014322332026, "from_links": "[5026]", "to_links": "[6471]", "activation": 4}, "1143": {"type": 1, "recurrent": "0", "mem_weight": null, "bias": -0.43209374502487913, "from_links": "[6136]", "to_links": "[4085]", "activation": 4}, "4834": {"type": 1, "recurrent": "0", "mem_weight": null, "bias": 0.4036434365725126, "from_links": "[4079]", "to_links": "[4026, 6038]", "activation": 0}, "3105": {"type": 1, "recurrent": "0", "mem_weight": null, "bias": 0.1261034626141131, "from_links": "[4872]", "to_links": "[7677, 5264]", "activation": 4}, "4135": {"type": 1, "recurrent": "1", "mem_weight": 0.3378745975694145, "bias": -0.09520755339130373, "from_links": "[]", "to_links": "[9671]", "activation": 0}, "7319": {"type": 1, "recurrent": "0", "mem_weight": null, "bias": 1, "from_links": "[2594, 6657]", "to_links": "[3637, 9076]", "activation": 0}, "1154": {"type": 1, "recurrent": "0", "mem_weight": null, "bias": 0.20590762921813519, "from_links": "[7747]", "to_links": "[2311, 1383]", "activation": 0}, "3424": {"type": 1, "recurrent": "0", "mem_weight": null, "bias": -0.23254473941005305, "from_links": "[6230]", "to_links": "[3070]", "activation": 1}, "8228": {"type": 1, "recurrent": "1", "mem_weight": 0.3088986432322306, "bias": -0.8367062087204544, "from_links": "[6544]", "to_links": "[8178]", "activation": 4}, "1194": {"type": 1, "recurrent": "0", "mem_weight": null, "bias": 0.7208637440587539, "from_links": "[1577]", "to_links": "[1440, 1368, 1138]", "activation": 4}, "1470": {"type": 1, "recurrent": "0", "mem_weight": null, "bias": -0.4603157934423792, "from_links": "[]", "to_links": "[]", "activation": 0}, "5555": {"type": 1, "recurrent": "0", "mem_weight": null, "bias": -0.9439892994730108, "from_links": "[]", "to_links": "[2658, 8124]", "activation": 0}, "5363": {"type": 1, "recurrent": "0", "mem_weight": null, "bias": 0.6408361259986747, "from_links": "[3300]", "to_links": "[4407]", "activation": 0}, "6868": {"type": 1, "recurrent": "0", "mem_weight": null, "bias": 0.20539695449324533, "from_links": "[1743]", "to_links": "[2292]", "activation": 0}, "5910": {"type": 1, "recurrent": "0", "mem_weight": null, "bias": 0.22495716295623142, "from_links": "[4304]", "to_links": "[9654]", "activation": 0}, "7438": {"type": 1, "recurrent": "0", "mem_weight": null, "bias": 0.2722336045614074, "from_links": "[3173]", "to_links": "[]", "activation": 0}, "1824": {"type": 1, "recurrent": "1", "mem_weight": 0.6320211899553696, "bias": -0.5832777740459587, "from_links": "[3385]", "to_links": "[2768]", "activation": 3}, "4844": {"type": 1, "recurrent": "0", "mem_weight": null, "bias": 1, "from_links": "[1540]", "to_links": "[2665]", "activation": 0}, "4479": {"type": 1, "recurrent": "0", "mem_weight": null, "bias": 0.3404875027401584, "from_links": "[6993]", "to_links": "[2280]", "activation": 0}, "3633": {"type": 1, "recurrent": "0", "mem_weight": null, "bias": -0.5266584062102204, "from_links": "[1122]", "to_links": "[6529]", "activation": 0}, "7776": {"type": 1, "recurrent": "0", "mem_weight": null, "bias": 0.562640430600602, "from_links": "[4237]", "to_links": "[1237]", "activation": 0}, "5089": {"type": 1, "recurrent": "0", "mem_weight": null, "bias": 0.10088203666176028, "from_links": "[8878]", "to_links": "[7068]", "activation": 0}, "2213": {"type": 1, "recurrent": "0", "mem_weight": null, "bias": 0.4286133339683573, "from_links": "[7954]", "to_links": "[3172]", "activation": 0}, "3874": {"type": 1, "recurrent": "0", "mem_weight": null, "bias": -1, "from_links": "[7346]", "to_links": "[7379]", "activation": 0}, "2584": {"type": 1, "recurrent": "0", "mem_weight": null, "bias": 0.24420398063698046, "from_links": "[3337]", "to_links": "[3685]", "activation": 0}, "6863": {"type": 1, "recurrent": "0", "mem_weight": null, "bias": -0.509785177208813, "from_links": "[4065]", "to_links": "[7660]", "activation": 2}, "1294": {"type": 1, "recurrent": "0", "mem_weight": null, "bias": -0.8167794917511487, "from_links": "[6699]", "to_links": "[5542]", "activation": 0}, "7368": {"type": 1, "recurrent": "0", "mem_weight": null, "bias": 1, "from_links": "[1104]", "to_links": "[8697]", "activation": 0}, "6291": {"type": 1, "recurrent": "0", "mem_weight": null, "bias": -0.4371410633202096, "from_links": "[5912]", "to_links": "[2359]", "activation": 0}, "9986": {"type": 1, "recurrent": "0", "mem_weight": null, "bias": -0.5882880646609789, "from_links": "[3877]", "to_links": "[7323]", "activation": 0}, "1770": {"type": 1, "recurrent": "0", "mem_weight": null, "bias": 0.8976834078722161, "from_links": "[9480]", "to_links": "[5301]", "activation": 0}}, "links": {"3071": {"weight": -0.3136112766212023, "from_node": 8513, "to_node": 3615}, "5656": {"weight": 0.612981608065969, "from_node": 9588, "to_node": 5010}, "6002": {"weight": -0.1973733638643042, "from_node": 9588, "to_node": 2051}, "2316": {"weight": -0.887273715873979, "from_node": 4178, "to_node": 5002}, "8378": {"weight": 0.5008670846562553, "from_node": 3138, "to_node": 5002}, "6471": {"weight": 0.35655901903002307, "from_node": 5609, "to_node": 4537}, "5026": {"weight": -0.12127547230961686, "from_node": 4537, "to_node": 8744}, "2985": {"weight": -1, "from_node": 3821, "to_node": 1103}, "4085": {"weight": 0.384122348681045, "from_node": 5287, "to_node": 1143}, "6136": {"weight": 0.12890950022035924, "from_node": 1143, "to_node": 6785}, "4026": {"weight": 0.1719826123895606, "from_node": 3546, "to_node": 4834}, "4079": {"weight": -0.92629946430534, "from_node": 4834, "to_node": 5010}, "7677": {"weight": -0.48118310045962964, "from_node": 8697, "to_node": 3105}, "4872": {"weight": -0.24124262976756994, "from_node": 3105, "to_node": 1103}, "9671": {"weight": -0.7739783195682033, "from_node": 3546, "to_node": 4135}, "5264": {"weight": -0.36166912524079403, "from_node": 3546, "to_node": 3105}, "6765": {"weight": -0.6666851473285996, "from_node": 4996, "to_node": 1103}, "3565": {"weight": 0.5264286824617418, "from_node": 8697, "to_node": 9981}, "3250": {"weight": -0.22010498330797718, "from_node": 3821, "to_node": 3138}, "3637": {"weight": -0.8756139943214486, "from_node": 9588, "to_node": 7319}, "2594": {"weight": -0.12057402652998588, "from_node": 7319, "to_node": 5010}, "2311": {"weight": 0.07182615058650384, "from_node": 4996, "to_node": 1154}, "7747": {"weight": -0.7106142055232119, "from_node": 1154, "to_node": 6785}, "3070": {"weight": 0.2623579836059453, "from_node": 8697, "to_node": 3424}, "6230": {"weight": -0.4355189514579029, "from_node": 3424, "to_node": 6785}, "8178": {"weight": 0.1511489154815743, "from_node": 1723, "to_node": 8228}, "6544": {"weight": -0.5839183789064647, "from_node": 8228, "to_node": 5010}, "1440": {"weight": 0.4882059205269691, "from_node": 1767, "to_node": 1194}, "1577": {"weight": 0.42814332573301733, "from_node": 1194, "to_node": 8744}, "1368": {"weight": 0.29976805635714876, "from_node": 1445, "to_node": 1194}, "1138": {"weight": -0.6374335148194746, "from_node": 1723, "to_node": 1194}, "2658": {"weight": -0.4871388235877287, "from_node": 5609, "to_node": 5555}, "4407": {"weight": -0.15588308450348828, "from_node": 5287, "to_node": 5363}, "3300": {"weight": -0.03576545220435396, "from_node": 5363, "to_node": 3615}, "2292": {"weight": 1, "from_node": 9588, "to_node": 6868}, "1743": {"weight": 0.7445721740294584, "from_node": 6868, "to_node": 5002}, "9654": {"weight": -0.5304260695111117, "from_node": 1767, "to_node": 5910}, "4304": {"weight": 0.05188000476007042, "from_node": 5910, "to_node": 5002}, "3173": {"weight": 1, "from_node": 7438, "to_node": 8744}, "2768": {"weight": -0.3270470945306901, "from_node": 4996, "to_node": 1824}, "3385": {"weight": -0.4851972427140733, "from_node": 1824, "to_node": 5010}, "2665": {"weight": 0.4344474329749068, "from_node": 4178, "to_node": 4844}, "1540": {"weight": 0.4889038475800731, "from_node": 4844, "to_node": 5002}, "2280": {"weight": -0.6122244195393626, "from_node": 6756, "to_node": 4479}, "6993": {"weight": -0.5073789056576637, "from_node": 4479, "to_node": 5002}, "1383": {"weight": -0.5002021210411626, "from_node": 8513, "to_node": 1154}, "6529": {"weight": -0.8697629327124767, "from_node": 6756, "to_node": 3633}, "1122": {"weight": -0.3500943825238575, "from_node": 3633, "to_node": 6785}, "1237": {"weight": -0.10488497389173174, "from_node": 4996, "to_node": 7776}, "4237": {"weight": -0.7551275173951147, "from_node": 7776, "to_node": 1103}, "7068": {"weight": -0.7572820382511349, "from_node": 6756, "to_node": 5089}, "8878": {"weight": 0.5364252477792163, "from_node": 5089, "to_node": 8744}, "7787": {"weight": 0.611778518391405, "from_node": 5609, "to_node": 3138}, "6038": {"weight": 0.06724564374009738, "from_node": 5609, "to_node": 4834}, "9076": {"weight": -0.12269570910814401, "from_node": 4996, "to_node": 7319}, "3172": {"weight": 0.20327960138336454, "from_node": 1445, "to_node": 2213}, "7954": {"weight": -0.08535421746872612, "from_node": 2213, "to_node": 1103}, "7379": {"weight": -0.0980411891969571, "from_node": 3546, "to_node": 3874}, "7346": {"weight": 0.5054174540120333, "from_node": 3874, "to_node": 8744}, "3685": {"weight": -0.3897053416590071, "from_node": 1723, "to_node": 2584}, "3337": {"weight": -0.7813381187562088, "from_node": 2584, "to_node": 8744}, "8124": {"weight": 0.3748397831238367, "from_node": 6756, "to_node": 5555}, "6657": {"weight": 0.11240996878643081, "from_node": 7319, "to_node": 3615}, "1150": {"weight": -0.03732304839919316, "from_node": 3546, "to_node": 1869}, "7660": {"weight": 0.0665493519447015, "from_node": 1723, "to_node": 6863}, "4065": {"weight": -0.21952059146164316, "from_node": 6863, "to_node": 5002}, "5542": {"weight": -0.5385610628031482, "from_node": 3546, "to_node": 1294}, "6699": {"weight": 0.10378397503654839, "from_node": 1294, "to_node": 5002}, "8697": {"weight": 0.11848807287298005, "from_node": 8513, "to_node": 7368}, "1104": {"weight": -0.4620562992011219, "from_node": 7368, "to_node": 6785}, "2359": {"weight": 0.13489617195548276, "from_node": 4996, "to_node": 6291}, "5912": {"weight": 0.2726645443471712, "from_node": 6291, "to_node": 3505}, "7323": {"weight": -1, "from_node": 1445, "to_node": 9986}, "3877": {"weight": -0.703361359401075, "from_node": 9986, "to_node": 8744}, "5301": {"weight": 0.2128623300011873, "from_node": 6756, "to_node": 1770}, "9480": {"weight": -0.19617324970020467, "from_node": 1770, "to_node": 3615}}}, "signature": [[9, 2, 3], [1990, 3071, 5656, 1459, 6002, 2316, 8378, 6471, 5026, 2985, 1213, 4085, 6136, 4026, 4079, 7677, 4872, 9671, 6186, 9696, 7890, 9866, 5264, 2842, 6765, 3565, 3250, 3637, 2594, 2311, 7747, 3070, 6230, 8178, 6544, 1555, 1440, 1577, 6674, 1924, 1368, 1138, 2658, 9667, 4407, 3300, 2292, 1743, 9654, 4304, 5588, 3173, 2768, 3385, 2665, 1540, 2280, 6993, 9009, 1383, 6654, 1363, 6529, 1122, 3684, 2819, 1237, 4237, 7068, 8878]], "genealogy": [["BZIZVF", 0, 1229], ["ZOIZVF", 2, 1752], ["BZIZFJ", 2, 1767], ["BZIZQJ", 2, 1769], ["BZIZZL", 2, 1773], ["BZNWVF", 2, 1783], ["BZIZIS", 3, 1813], ["BZIZVY", 3, 1887], ["BZOJVY", 4, 1945], ["BZIZMF", 4, 1947], ["BZXFVY", 4, 2122], ["BZIZSU", 4, 2133], ["BZTDVY", 5, 2278], ["BZAXVY", 5, 2316], ["BZNSVY", 6, 2401], ["BZAXDY", 6, 2556], ["BZRUVY", 6, 2560], ["BZJOVY", 6, 2598], ["SSAXDY", 7, 2937], ["BZKADY", 7, 3041], ["UKAXDY", 7, 3044], ["BZAXNK", 7, 3059], ["BZAXVO", 7, 3083], ["BZBODY", 8, 3110]]}