{"name": "CZLAOC", "gen": 17, "mutations": 10, "size": 6.0, "power": 1, "food": 9, "speed": 5, "eyes": 2, "color0": [0, 0, 0, 255], "color1": [135, 206, 235, 255], "color2": [0, 0, 255, 255], "color3": [255, 0, 0, 255], "signature": [[6, 5, 10, 2, 1, 8], [7968, 9346, 5508, 2698, 7491, 3437, 8427, 6090, 8798, 6742, 6259, 1928, 3513, 5336, 7400, 1111, 1649, 8420, 1245]], "genealogy": [["CZLAOC", 0, 3549]], "first_one": "CZLAOC", "spike_num": 7, "neuro": {"layer_num": 9, "node_num": 2, "link_num": 24, "layers": {"0": {"type": 0, "nodes": "[1445, 1478, 3735, 6506, 8031, 6951, 7398, 2148, 5206, 9208, 1483, 6699, 5256, 6371, 9366]"}, "1": {"type": 1, "nodes": "[]"}, "2": {"type": 1, "nodes": "[]"}, "3": {"type": 1, "nodes": "[]"}, "4": {"type": 1, "nodes": "[]"}, "5": {"type": 1, "nodes": "[4276]"}, "6": {"type": 1, "nodes": "[]"}, "7": {"type": 1, "nodes": "[7752]"}, "8": {"type": 2, "nodes": "[6305, 9926, 3631, 1725, 5011, 8599]"}}, "nodes": {"1445": {"type": 0, "recurrent": "0", "memory_size": "0", "bias": 0.1107493643767181, "from_links": "[2698, 1111]", "to_links": "[]", "activation": 0}, "1478": {"type": 0, "recurrent": "0", "memory_size": "0", "bias": 0.5460925388913171, "from_links": "[7491, 6742, 1873]", "to_links": "[]", "activation": 0}, "3735": {"type": 0, "recurrent": "1", "memory_size": "11", "bias": 1, "from_links": "[]", "to_links": "[]", "activation": 0}, "6506": {"type": 0, "recurrent": "0", "memory_size": "0", "bias": -0.7191933787811587, "from_links": "[3437]", "to_links": "[]", "activation": 0}, "8031": {"type": 0, "recurrent": "0", "memory_size": "0", "bias": 0.1019002997930099, "from_links": "[]", "to_links": "[]", "activation": 0}, "6951": {"type": 0, "recurrent": "0", "memory_size": "0", "bias": 0.3994133170332916, "from_links": "[8427]", "to_links": "[]", "activation": 0}, "7398": {"type": 0, "recurrent": "0", "memory_size": "0", "bias": -0.6082962637472101, "from_links": "[6259, 5336, 1904]", "to_links": "[]", "activation": 0}, "2148": {"type": 0, "recurrent": "1", "memory_size": "7", "bias": -0.09122362522265817, "from_links": "[6090]", "to_links": "[]", "activation": 0}, "5206": {"type": 0, "recurrent": "0", "memory_size": "0", "bias": 0.13370485440837987, "from_links": "[7968, 1928, 7400]", "to_links": "[]", "activation": 0}, "9208": {"type": 0, "recurrent": "0", "memory_size": "0", "bias": 0.09856542901108507, "from_links": "[9346]", "to_links": "[]", "activation": 0}, "1483": {"type": 0, "recurrent": "0", "memory_size": "0", "bias": -0.4599733950017249, "from_links": "[1245]", "to_links": "[]", "activation": 0}, "6699": {"type": 0, "recurrent": "0", "memory_size": "0", "bias": -0.5582605803995722, "from_links": "[8798, 3513, 3088]", "to_links": "[]", "activation": 0}, "5256": {"type": 0, "recurrent": "1", "memory_size": "6", "bias": -1, "from_links": "[5508]", "to_links": "[]", "activation": 0}, "6371": {"type": 0, "recurrent": "0", "memory_size": "0", "bias": 0.25903717278632477, "from_links": "[8420, 3634]", "to_links": "[]", "activation": 0}, "9366": {"type": 0, "recurrent": "0", "memory_size": "0", "bias": 0.492285421200622, "from_links": "[]", "to_links": "[]", "activation": 0}, "6305": {"type": 2, "recurrent": "0", "memory_size": "0", "bias": 0.4393308841400489, "from_links": "[]", "to_links": "[7968, 9346, 5508]", "activation": 0}, "9926": {"type": 2, "recurrent": "0", "memory_size": "0", "bias": -0.035244535093184336, "from_links": "[]", "to_links": "[2698, 7491, 3437, 8427, 6090, 8798]", "activation": 0}, "3631": {"type": 2, "recurrent": "1", "memory_size": "1", "bias": -0.3051659166296658, "from_links": "[]", "to_links": "[6742, 6259, 1928, 3513, 3291, 3634]", "activation": 0}, "1725": {"type": 2, "recurrent": "0", "memory_size": "0", "bias": -0.24953998145313905, "from_links": "[]", "to_links": "[5336, 7400, 9065]", "activation": 0}, "5011": {"type": 2, "recurrent": "0", "memory_size": "0", "bias": 0.06466965640200775, "from_links": "[]", "to_links": "[1111, 8420, 1904]", "activation": 0}, "8599": {"type": 2, "recurrent": "1", "memory_size": "1", "bias": -0.43949031850332804, "from_links": "[]", "to_links": "[1245]", "activation": 0}, "4276": {"type": 1, "recurrent": "0", "memory_size": "0", "bias": -0.05733789729133839, "from_links": "[3291]", "to_links": "[3088]", "activation": 0}, "7752": {"type": 1, "recurrent": "0", "memory_size": "0", "bias": 0.5089033854551092, "from_links": "[9065]", "to_links": "[1873]", "activation": 0}}, "links": {"7968": {"weight": 0.8081070983177717, "from_node": 5206, "to_node": 6305}, "9346": {"weight": -0.2750526185829105, "from_node": 9208, "to_node": 6305}, "5508": {"weight": 0.35204750372198274, "from_node": 5256, "to_node": 6305}, "2698": {"weight": -0.40552352475762976, "from_node": 1445, "to_node": 9926}, "7491": {"weight": 0.7383536830077797, "from_node": 1478, "to_node": 9926}, "3437": {"weight": -0.850338583319474, "from_node": 6506, "to_node": 9926}, "8427": {"weight": -0.1565567315247086, "from_node": 6951, "to_node": 9926}, "6090": {"weight": -0.34658392782710523, "from_node": 2148, "to_node": 9926}, "8798": {"weight": 0.8158034005661604, "from_node": 6699, "to_node": 9926}, "6742": {"weight": -0.18391576901750112, "from_node": 1478, "to_node": 3631}, "6259": {"weight": 0.018861636631627852, "from_node": 7398, "to_node": 3631}, "1928": {"weight": -0.7901963442080354, "from_node": 5206, "to_node": 3631}, "3513": {"weight": 1, "from_node": 6699, "to_node": 3631}, "5336": {"weight": 0.5243323342138062, "from_node": 7398, "to_node": 1725}, "7400": {"weight": -0.09611613904889137, "from_node": 5206, "to_node": 1725}, "1111": {"weight": 0.35674009697064263, "from_node": 1445, "to_node": 5011}, "8420": {"weight": 1, "from_node": 6371, "to_node": 5011}, "1245": {"weight": -0.8654246995381814, "from_node": 1483, "to_node": 8599}, "3088": {"weight": 0.021658924395615103, "from_node": 6699, "to_node": 4276}, "3291": {"weight": -0.10223806114371907, "from_node": 4276, "to_node": 3631}, "1904": {"weight": 0.1631143072648898, "from_node": 7398, "to_node": 5011}, "3634": {"weight": -0.16127922355522029, "from_node": 6371, "to_node": 3631}, "1873": {"weight": -0.5526941946404205, "from_node": 1478, "to_node": 7752}, "9065": {"weight": 0.08739037504188427, "from_node": 7752, "to_node": 1725}}}}