{"name": "IIQRRR", "gen": 0, "mutations": 3, "size": 10.0, "power": 7, "food": 5, "speed": 10, "eyes": 4, "color0": [0, 0, 0, 255], "color1": [135, 206, 235, 255], "color2": [0, 0, 255, 255], "color3": [255, 0, 0, 255], "neuro": {"layer_num": 9, "node_num": 0, "link_num": 0, "layers": {"0": {"type": 0, "nodes": "[5632, 7346, 7441, 9163, 5712, 1658, 1915, 3897, 1269, 5630, 4112, 1288, 7670, 7236]"}, "1": {"type": 1, "nodes": "[]"}, "2": {"type": 1, "nodes": "[]"}, "3": {"type": 1, "nodes": "[]"}, "4": {"type": 1, "nodes": "[]"}, "5": {"type": 1, "nodes": "[]"}, "6": {"type": 1, "nodes": "[]"}, "7": {"type": 1, "nodes": "[]"}, "8": {"type": 2, "nodes": "[6720, 7590, 5785, 6240, 6969]"}}, "nodes": {"5632": {"type": 0, "recurrent": "0", "mem_weight": null, "bias": 0.30453986596769594, "from_links": "[1010]", "to_links": "[]", "activation": 0}, "7346": {"type": 0, "recurrent": "0", "mem_weight": null, "bias": -0.44130276105865984, "from_links": "[5194]", "to_links": "[]", "activation": 0}, "7441": {"type": 0, "recurrent": "0", "mem_weight": null, "bias": 0.8000535148775964, "from_links": "[7949, 5197, 6913]", "to_links": "[]", "activation": 0}, "9163": {"type": 0, "recurrent": "0", "mem_weight": null, "bias": -0.10054469505482518, "from_links": "[1820]", "to_links": "[]", "activation": 0}, "5712": {"type": 0, "recurrent": "0", "mem_weight": null, "bias": -0.08739860767120998, "from_links": "[8610, 1414, 3687]", "to_links": "[]", "activation": 0}, "1658": {"type": 0, "recurrent": "0", "mem_weight": null, "bias": -0.39916071705263684, "from_links": "[]", "to_links": "[]", "activation": 0}, "1915": {"type": 0, "recurrent": "0", "mem_weight": null, "bias": -0.14059817015542914, "from_links": "[5979, 1828]", "to_links": "[]", "activation": 0}, "3897": {"type": 0, "recurrent": "0", "mem_weight": null, "bias": 0.5141264832116221, "from_links": "[]", "to_links": "[]", "activation": 0}, "1269": {"type": 0, "recurrent": "0", "mem_weight": null, "bias": 0.25669613298315974, "from_links": "[4828]", "to_links": "[]", "activation": 0}, "5630": {"type": 0, "recurrent": "0", "mem_weight": null, "bias": -0.5234241664376214, "from_links": "[6232, 1887]", "to_links": "[]", "activation": 0}, "4112": {"type": 0, "recurrent": "0", "mem_weight": null, "bias": -1, "from_links": "[7286, 6284]", "to_links": "[]", "activation": 0}, "1288": {"type": 0, "recurrent": "0", "mem_weight": null, "bias": 0.02463602381748008, "from_links": "[]", "to_links": "[]", "activation": 0}, "7670": {"type": 0, "recurrent": "0", "mem_weight": null, "bias": -0.5444553627928089, "from_links": "[1046, 3934]", "to_links": "[]", "activation": 0}, "7236": {"type": 0, "recurrent": "0", "mem_weight": null, "bias": 0.7376041187179357, "from_links": "[]", "to_links": "[]", "activation": 0}, "6720": {"type": 2, "recurrent": "0", "mem_weight": null, "bias": 0.5289587367623395, "from_links": "[]", "to_links": "[7949, 1820, 5979, 4828]", "activation": 0}, "7590": {"type": 2, "recurrent": "0", "mem_weight": null, "bias": 0.46575931624776284, "from_links": "[]", "to_links": "[8610, 6232, 7286, 1046]", "activation": 0}, "5785": {"type": 2, "recurrent": "0", "mem_weight": null, "bias": -0.9912286760292283, "from_links": "[]", "to_links": "[5197, 1414, 1887, 6284]", "activation": 0}, "6240": {"type": 2, "recurrent": "0", "mem_weight": null, "bias": 0.44655885876352247, "from_links": "[]", "to_links": "[1010, 6913]", "activation": 0}, "6969": {"type": 2, "recurrent": "0", "mem_weight": null, "bias": 0.14918413645145884, "from_links": "[]", "to_links": "[5194, 3687, 1828, 3934]", "activation": 0}}, "links": {"7949": {"weight": -0.30802674416183834, "from_node": 7441, "to_node": 6720}, "1820": {"weight": -0.36971995502349536, "from_node": 9163, "to_node": 6720}, "5979": {"weight": 0.3093739118757338, "from_node": 1915, "to_node": 6720}, "4828": {"weight": 0.34104533812970683, "from_node": 1269, "to_node": 6720}, "8610": {"weight": 0.9928375867122226, "from_node": 5712, "to_node": 7590}, "6232": {"weight": -1, "from_node": 5630, "to_node": 7590}, "7286": {"weight": -0.7211187543043655, "from_node": 4112, "to_node": 7590}, "1046": {"weight": 0.0013988657038107005, "from_node": 7670, "to_node": 7590}, "5197": {"weight": 0.0353906114969207, "from_node": 7441, "to_node": 5785}, "1414": {"weight": -0.07775782903710185, "from_node": 5712, "to_node": 5785}, "1887": {"weight": 0.41438730561297793, "from_node": 5630, "to_node": 5785}, "6284": {"weight": 0.8447295085937149, "from_node": 4112, "to_node": 5785}, "1010": {"weight": -1, "from_node": 5632, "to_node": 6240}, "6913": {"weight": -1, "from_node": 7441, "to_node": 6240}, "5194": {"weight": 0.09504813914057818, "from_node": 7346, "to_node": 6969}, "3687": {"weight": -0.33122731943524497, "from_node": 5712, "to_node": 6969}, "1828": {"weight": 0.449417799134824, "from_node": 1915, "to_node": 6969}, "3934": {"weight": 0.5817016822838909, "from_node": 7670, "to_node": 6969}}}, "signature": [[10, 7, 5, 4], [7949, 1820, 5979, 4828, 8610, 6232, 7286, 1046, 5197, 1414, 1887, 6284, 1010, 6913, 5194, 3687, 1828, 3934]], "genealogy": [["IIQRRR", 0, 5635]]}