{"name": "ZUJSDZ", "gen": 137, "mutations": 4, "size": 10.0, "power": 9, "food": 10, "speed": 7, "eyes": 4, "color0": [0, 0, 0, 255], "color1": [135, 206, 235, 255], "color2": [0, 0, 255, 255], "color3": [255, 0, 0, 255], "signature": [[8, 10, 10, 5, 8, 8], [6386, 2396, 1551, 9393, 9398, 4279, 1248, 6860, 7841, 3751, 2969, 1636, 6794, 5615, 3624, 2937, 9640, 5126, 2049, 7355, 2306, 4226, 1787, 2973, 6649, 8222, 2063, 1135, 1094, 1103, 8337, 6426, 1027, 1689, 6397, 3247, 3954]], "genealogy": [["ZUJSVS", 0, 6540], ["ZUJSDU", 50, 22121], ["ZUJSDZ", 73, 29912]], "first_one": "ZUJSVS", "spike_num": 1, "neuro": {"layer_num": 9, "node_num": 8, "link_num": 40, "layers": {"0": {"type": 0, "nodes": "[1024, 7387, 1373, 4280, 6298, 5538, 5691, 3064, 1359, 4788, 1144, 5198, 3714, 2655, 6394]"}, "1": {"type": 1, "nodes": "[]"}, "2": {"type": 1, "nodes": "[9538, 6889, 2136]"}, "3": {"type": 1, "nodes": "[]"}, "4": {"type": 1, "nodes": "[4347]"}, "5": {"type": 1, "nodes": "[5600]"}, "6": {"type": 1, "nodes": "[5533]"}, "7": {"type": 1, "nodes": "[6133, 1635]"}, "8": {"type": 2, "nodes": "[1710, 8233, 2395, 1770, 6878, 6725]"}}, "nodes": {"1024": {"type": 0, "recurrent": "0", "memory_size": "0", "bias": 1, "from_links": "[2969, 4256]", "to_links": "[]", "activation": 0}, "7387": {"type": 0, "recurrent": "1", "memory_size": "3", "bias": -0.026430813010441014, "from_links": "[7113]", "to_links": "[]", "activation": 0}, "1373": {"type": 0, "recurrent": "0", "memory_size": "0", "bias": 0.6637773671543077, "from_links": "[9398, 4775]", "to_links": "[]", "activation": 0}, "4280": {"type": 0, "recurrent": "0", "memory_size": "0", "bias": -0.45763026096317194, "from_links": "[2306, 1103, 1027, 1689]", "to_links": "[]", "activation": 0}, "6298": {"type": 0, "recurrent": "0", "memory_size": "0", "bias": -0.9570065612382406, "from_links": "[4279, 2937, 1984]", "to_links": "[]", "activation": 0}, "5538": {"type": 0, "recurrent": "1", "memory_size": "6", "bias": -0.14365023002781777, "from_links": "[2396, 3624, 5126]", "to_links": "[]", "activation": 0}, "5691": {"type": 0, "recurrent": "0", "memory_size": "0", "bias": 1, "from_links": "[7841]", "to_links": "[]", "activation": 0}, "3064": {"type": 0, "recurrent": "0", "memory_size": "0", "bias": -1, "from_links": "[1248, 7355]", "to_links": "[]", "activation": 0}, "1359": {"type": 0, "recurrent": "1", "memory_size": "14", "bias": 0.33905766723703196, "from_links": "[6386, 9352]", "to_links": "[]", "activation": 0}, "4788": {"type": 0, "recurrent": "1", "memory_size": "11", "bias": 0.20540329751112918, "from_links": "[1551, 3751]", "to_links": "[]", "activation": 0}, "1144": {"type": 0, "recurrent": "0", "memory_size": "0", "bias": -0.49185762192647975, "from_links": "[9393, 2165]", "to_links": "[]", "activation": 0}, "5198": {"type": 0, "recurrent": "1", "memory_size": "3", "bias": 0.911212724112331, "from_links": "[6794, 8222, 8901]", "to_links": "[]", "activation": 0}, "3714": {"type": 0, "recurrent": "0", "memory_size": "0", "bias": -0.6768382613675838, "from_links": "[3247]", "to_links": "[]", "activation": 0}, "2655": {"type": 0, "recurrent": "1", "memory_size": "7", "bias": 0.3044430874208803, "from_links": "[1787, 1135]", "to_links": "[]", "activation": 0}, "6394": {"type": 0, "recurrent": "0", "memory_size": "0", "bias": 0.33511410789885343, "from_links": "[5615, 3589]", "to_links": "[]", "activation": 0}, "1710": {"type": 2, "recurrent": "1", "memory_size": "8", "bias": 0.2630962999808045, "from_links": "[]", "to_links": "[6386, 7355, 6397, 3954, 4256]", "activation": 0}, "8233": {"type": 2, "recurrent": "1", "memory_size": "3", "bias": 0.037144213467344686, "from_links": "[]", "to_links": "[2396, 1551, 9393]", "activation": 0}, "2395": {"type": 2, "recurrent": "0", "memory_size": "0", "bias": 0.049129496387063765, "from_links": "[]", "to_links": "[9398, 4279, 1248, 1787]", "activation": 0}, "1770": {"type": 2, "recurrent": "1", "memory_size": "14", "bias": 1, "from_links": "[]", "to_links": "[7841, 3751, 2973, 2063, 8901]", "activation": 0}, "6878": {"type": 2, "recurrent": "0", "memory_size": "0", "bias": -0.40205109576202663, "from_links": "[]", "to_links": "[2969, 6794, 5615, 2937, 2049, 1599, 9352]", "activation": 0}, "6725": {"type": 2, "recurrent": "1", "memory_size": "5", "bias": -0.27257880330978834, "from_links": "[]", "to_links": "[3624, 4226, 1094]", "activation": 0}, "9538": {"type": 1, "recurrent": "1", "memory_size": "10", "bias": -0.9301999577460431, "from_links": "[2049]", "to_links": "[5126, 1103]", "activation": 0}, "6133": {"type": 1, "recurrent": "1", "memory_size": "14", "bias": 0.1956960471231356, "from_links": "[4226]", "to_links": "[2306]", "activation": 0}, "6889": {"type": 1, "recurrent": "0", "memory_size": "0", "bias": -0.6296085894352903, "from_links": "[2973]", "to_links": "[]", "activation": 0}, "2136": {"type": 1, "recurrent": "0", "memory_size": "0", "bias": -1, "from_links": "[2063]", "to_links": "[8222, 1027, 1984]", "activation": 0}, "5600": {"type": 1, "recurrent": "0", "memory_size": "0", "bias": -0.22843367592377267, "from_links": "[1094]", "to_links": "[1135]", "activation": 0}, "5533": {"type": 1, "recurrent": "0", "memory_size": "0", "bias": -0.665616007781307, "from_links": "[6397]", "to_links": "[1689]", "activation": 0}, "1635": {"type": 1, "recurrent": "0", "memory_size": "0", "bias": -0.7457486744739301, "from_links": "[3954]", "to_links": "[3247, 7113]", "activation": 0}, "4347": {"type": 1, "recurrent": "0", "memory_size": "0", "bias": 0.437272538729354, "from_links": "[1599]", "to_links": "[2165, 3589, 4775]", "activation": 0}}, "links": {"6386": {"weight": -0.058106344024396184, "from_node": 1359, "to_node": 1710}, "2396": {"weight": 0.8044210981403324, "from_node": 5538, "to_node": 8233}, "1551": {"weight": -0.007494520340629375, "from_node": 4788, "to_node": 8233}, "9393": {"weight": 0.1764745946193378, "from_node": 1144, "to_node": 8233}, "9398": {"weight": 0.5579781626217882, "from_node": 1373, "to_node": 2395}, "4279": {"weight": -0.3546563474781244, "from_node": 6298, "to_node": 2395}, "1248": {"weight": -0.1158867358189572, "from_node": 3064, "to_node": 2395}, "7841": {"weight": 0.42103996255540677, "from_node": 5691, "to_node": 1770}, "3751": {"weight": 0.8745591792047323, "from_node": 4788, "to_node": 1770}, "2969": {"weight": -0.500449265309568, "from_node": 1024, "to_node": 6878}, "6794": {"weight": -0.19773020459160207, "from_node": 5198, "to_node": 6878}, "5615": {"weight": -0.291162010238851, "from_node": 6394, "to_node": 6878}, "3624": {"weight": 0.8621910345977069, "from_node": 5538, "to_node": 6725}, "2937": {"weight": -0.0375377335429008, "from_node": 6298, "to_node": 6878}, "5126": {"weight": -0.08155670376333508, "from_node": 5538, "to_node": 9538}, "2049": {"weight": -0.503683229994669, "from_node": 9538, "to_node": 6878}, "7355": {"weight": 0.582333714076864, "from_node": 3064, "to_node": 1710}, "2306": {"weight": 0.008819678160738672, "from_node": 4280, "to_node": 6133}, "4226": {"weight": -0.1303390303343718, "from_node": 6133, "to_node": 6725}, "1787": {"weight": -0.01553432347690959, "from_node": 2655, "to_node": 2395}, "2973": {"weight": -1, "from_node": 6889, "to_node": 1770}, "8222": {"weight": -0.17989381437510968, "from_node": 5198, "to_node": 2136}, "2063": {"weight": 0.3907932174632349, "from_node": 2136, "to_node": 1770}, "1135": {"weight": -0.3009206486805378, "from_node": 2655, "to_node": 5600}, "1094": {"weight": -1, "from_node": 5600, "to_node": 6725}, "1103": {"weight": 0.0064714259099486904, "from_node": 4280, "to_node": 9538}, "1027": {"weight": -0.1921274788292053, "from_node": 4280, "to_node": 2136}, "1689": {"weight": -0.6161602307887536, "from_node": 4280, "to_node": 5533}, "6397": {"weight": 0.18437362077850042, "from_node": 5533, "to_node": 1710}, "3247": {"weight": -0.36427167374119923, "from_node": 3714, "to_node": 1635}, "3954": {"weight": -0.5352261212379157, "from_node": 1635, "to_node": 1710}, "2165": {"weight": 0.4167876551325464, "from_node": 1144, "to_node": 4347}, "1599": {"weight": 0.646109318066258, "from_node": 4347, "to_node": 6878}, "8901": {"weight": 0.8269815225360556, "from_node": 5198, "to_node": 1770}, "7113": {"weight": -1, "from_node": 7387, "to_node": 1635}, "1984": {"weight": -0.4758718767959558, "from_node": 6298, "to_node": 2136}, "3589": {"weight": -0.5205431889626192, "from_node": 6394, "to_node": 4347}, "4256": {"weight": -1, "from_node": 1024, "to_node": 1710}, "4775": {"weight": 1, "from_node": 1373, "to_node": 4347}, "9352": {"weight": 0.17884176622768772, "from_node": 1359, "to_node": 6878}}}}